ultra_framework/__init__.py
ultra_framework/version.py
ultra_framework/database/__init__.py
ultra_framework/database/session_factory.py
ultra_framework/entities/__init__.py
ultra_framework/entities/sql_entity.py
ultra_framework/mixins/__init__.py
ultra_framework/mixins/session_mixin.py
ultra_framework/models/__init__.py
ultra_framework/models/user.py
ultra_framework/repositories/__init__.py
ultra_framework/repositories/base_repository_factory.py
ultra_framework/repositories/crud_repository.py
ultra_framework/utils/__init__.py
ultra_framework/utils/dependencies.py
ultra_framework/utils/exceptions.py
ultra_framework/utils/jwt_handler.py
ultra_framework/utils/pagination.py
ultra_framework-0.0.13.dist-info/METADATA
ultra_framework-0.0.13.dist-info/WHEEL
ultra_framework-0.0.13.dist-info/top_level.txt
ultra_framework-0.0.13.dist-info/RECORD
