Metadata-Version: 2.1
Name: ultra_framework
Version: 0.0.13
Summary: Framework based on FastAPI.
Author: Giorgio Ripani
Author-email: Giorgio <g.ripani93@gmail.com>
Maintainer-email: Giorgio <g.ripani93@gmail.com>
Requires-Python: >=3.12
Requires-Dist: sqlalchemy>=2.0.36
Requires-Dist: pydantic>=2.8.2
Requires-Dist: fastapi>=0.114.0
Requires-Dist: pyjwt>=2.9.0
